ml_dl_models/__init__.py
ml_dl_models/models.py
ml_dl_models-1.0.3.dist-info/LICENSE
ml_dl_models-1.0.3.dist-info/METADATA
ml_dl_models-1.0.3.dist-info/WHEEL
ml_dl_models-1.0.3.dist-info/top_level.txt
ml_dl_models-1.0.3.dist-info/RECORD
