Metadata-Version: 2.1
Name: ml-dl-models
Version: 1.0.3
Summary: Module to access machine learning and deep learning module
Home-page: https://github.com/laxmanmaharjan/ml-dl-models
Author: Laxman Maharjan
Author-email: lxmnmrzn17@gmail.com
License: UNKNOWN
Project-URL: Bug Tracker, https://github.com/laxmanmaharjan/ml-dl-models/issues
Platform: UNKNOWN
Classifier: Programming Language :: Python :: 3
Classifier: License :: OSI Approved :: MIT License
Classifier: Operating System :: OS Independent
Requires-Python: >=3.6
License-File: LICENSE
Requires-Dist: requests
Requires-Dist: music21 (>=7)
